{
  "meta": {
    "version": "V11.1",
    "updated": "2026-03-05",
    "total_dimensions": 95,
    "domains": {
      "需求端": 35,
      "交付端": 35,
      "控制变量": 25
    },
    "author": "#cook",
    "description": "菜谱维度字典表 - 完整 10 字段结构"
  },
  "dimensions": [
    {"dimension_id":"DEMAND_SCENE_001","domain":"需求端","dimension_name_cn":"用餐时段","dimension_name_en":"meal_period","definition":"菜谱适合的消费时间段","value_type":"枚举","allowed_values":["早餐","午餐","晚餐","夜宵","下午茶"],"source_fields":["name","tags","cook_time"],"parse_method":"规则","remarks":"根据菜名和烹饪时长推断","ui_component":"select","default_value":"午餐","weight":1.0},
    {"dimension_id":"DEMAND_SCENE_002","domain":"需求端","dimension_name_cn":"消费场景","dimension_name_en":"consumption_scenario","definition":"菜谱适用的消费场景类型","value_type":"枚举","allowed_values":["堂食","外卖","团餐","宴会","自助","快餐"],"source_fields":["portion_size","cook_time"],"parse_method":"规则","remarks":"根据份量和出餐速度判断","ui_component":"select","default_value":"堂食","weight":1.0},
    {"dimension_id":"DEMAND_SCENE_003","domain":"需求端","dimension_name_cn":"业态场地","dimension_name_en":"venue_type","definition":"菜谱适合的经营场所类型","value_type":"枚举","allowed_values":["餐厅","酒店","机场","高铁","学校","医院","企业食堂","景区"],"source_fields":["complexity","cook_time","equipment"],"parse_method":"规则","remarks":"根据复杂度和设备要求判断","ui_component":"select","default_value":"餐厅","weight":1.0},
    {"dimension_id":"DEMAND_SCENE_004","domain":"需求端","dimension_name_cn":"高峰压力","dimension_name_en":"peak_pressure","definition":"菜谱在高峰期的制作压力等级","value_type":"枚举","allowed_values":["低","中","高"],"source_fields":["cook_time","manual_count","steps"],"parse_method":"计算","remarks":"cook_time<180s 且 manual_count<=3→低","ui_component":"select","default_value":"中","weight":0.8},
    {"dimension_id":"DEMAND_SCENE_005","domain":"需求端","dimension_name_cn":"出餐要求","dimension_name_en":"serving_speed_requirement","definition":"菜谱对出餐速度的要求等级","value_type":"枚举","allowed_values":["极快","快","标准","可慢"],"source_fields":["cook_time"],"parse_method":"规则","remarks":"<120s→极快，120-180s→快，180-360s→标准","ui_component":"select","default_value":"标准","weight":1.0},
    {"dimension_id":"DEMAND_BUSINESS_001","domain":"需求端","dimension_name_cn":"价格带","dimension_name_en":"price_range","definition":"菜谱的市场价格定位","value_type":"枚举","allowed_values":["平价","中端","精品","高端"],"source_fields":["ingredients","cook_time","complexity"],"parse_method":"计算","remarks":"根据食材成本 + 人工成本估算","ui_component":"select","default_value":"中端","weight":1.0},
    {"dimension_id":"DEMAND_BUSINESS_002","domain":"需求端","dimension_name_cn":"成本敏感度","dimension_name_en":"cost_sensitivity","definition":"菜谱对成本变化的敏感程度","value_type":"枚举","allowed_values":["高","中","低"],"source_fields":["ingredients","price_range"],"parse_method":"规则","remarks":"平价菜品→高敏感度","ui_component":"select","default_value":"中","weight":0.8},
    {"dimension_id":"DEMAND_BUSINESS_003","domain":"需求端","dimension_name_cn":"毛利属性","dimension_name_en":"margin_type","definition":"菜谱在商业模型中的毛利定位","value_type":"枚举","allowed_values":["引流款","常规款","利润款","招牌款"],"source_fields":["price_range","popularity","cost"],"parse_method":"计算","remarks":"低价高销→引流款","ui_component":"select","default_value":"常规款","weight":1.0},
    {"dimension_id":"DEMAND_BUSINESS_004","domain":"需求端","dimension_name_cn":"复购频次","dimension_name_en":"repurchase_frequency","definition":"菜品的预期复购频率","value_type":"枚举","allowed_values":["高频","中频","低频"],"source_fields":["cuisine_type","flavor_type"],"parse_method":"规则","remarks":"家常菜→高频，宴会菜→低频","ui_component":"select","default_value":"中频","weight":0.8},
    {"dimension_id":"DEMAND_BUSINESS_005","domain":"需求端","dimension_name_cn":"标准化要求","dimension_name_en":"standardization_requirement","definition":"菜谱对标准化制作的要求程度","value_type":"枚举","allowed_values":["高","中","低"],"source_fields":["manual_count","automation_ratio"],"parse_method":"计算","remarks":"自动化率高→高标准化","ui_component":"select","default_value":"中","weight":0.9},
    {"dimension_id":"DEMAND_EXPERIENCE_001","domain":"需求端","dimension_name_cn":"味型","dimension_name_en":"flavor_type","definition":"菜品的主要口味类型","value_type":"枚举","allowed_values":["咸鲜","麻辣","香辣","酸辣","酸甜","清淡","蒜香","酱香","咖喱","黑椒"],"source_fields":["name","ingredients","seasonings"],"parse_method":"模型","remarks":"AI 识别 + 规则","ui_component":"select","default_value":"咸鲜","weight":1.0},
    {"dimension_id":"DEMAND_EXPERIENCE_002","domain":"需求端","dimension_name_cn":"辣度","dimension_name_en":"spiciness_level","definition":"菜品的辣度等级 (0-5)","value_type":"数值","allowed_values":[0,1,2,3,4,5],"source_fields":["ingredients","seasonings"],"parse_method":"计算","remarks":"辣椒用量综合计算","ui_component":"slider","default_value":0,"weight":1.0,"min_value":0,"max_value":5},
    {"dimension_id":"DEMAND_EXPERIENCE_003","domain":"需求端","dimension_name_cn":"麻度","dimension_name_en":"numbing_level","definition":"菜品的麻度等级 (0-5)","value_type":"数值","allowed_values":[0,1,2,3,4,5],"source_fields":["ingredients","seasonings"],"parse_method":"计算","remarks":"花椒/麻椒用量计算","ui_component":"slider","default_value":0,"weight":1.0,"min_value":0,"max_value":5},
    {"dimension_id":"DEMAND_EXPERIENCE_004","domain":"需求端","dimension_name_cn":"咸度","dimension_name_en":"saltiness_level","definition":"菜品的咸度等级 (0-5)","value_type":"数值","allowed_values":[0,1,2,3,4,5],"source_fields":["seasonings"],"parse_method":"计算","remarks":"盐 + 酱油 + 酱料综合","ui_component":"slider","default_value":3,"weight":1.0,"min_value":0,"max_value":5},
    {"dimension_id":"DEMAND_EXPERIENCE_005","domain":"需求端","dimension_name_cn":"甜度","dimension_name_en":"sweetness_level","definition":"菜品的甜度等级 (0-5)","value_type":"数值","allowed_values":[0,1,2,3,4,5],"source_fields":["seasonings"],"parse_method":"计算","remarks":"糖 + 甜味调料","ui_component":"slider","default_value":0,"weight":1.0,"min_value":0,"max_value":5},
    {"dimension_id":"DEMAND_EXPERIENCE_006","domain":"需求端","dimension_name_cn":"酸度","dimension_name_en":"sourness_level","definition":"菜品的酸度等级 (0-5)","value_type":"数值","allowed_values":[0,1,2,3,4,5],"source_fields":["seasonings"],"parse_method":"计算","remarks":"醋 + 酸味调料","ui_component":"slider","default_value":0,"weight":1.0,"min_value":0,"max_value":5},
    {"dimension_id":"DEMAND_EXPERIENCE_007","domain":"需求端","dimension_name_cn":"油润感","dimension_name_en":"oiliness_level","definition":"菜品的油润程度等级 (0-5)","value_type":"数值","allowed_values":[0,1,2,3,4,5],"source_fields":["ingredients","cooking_method"],"parse_method":"计算","remarks":"用油量 + 食材含油量","ui_component":"slider","default_value":3,"weight":0.9,"min_value":0,"max_value":5},
    {"dimension_id":"DEMAND_EXPERIENCE_008","domain":"需求端","dimension_name_cn":"锅气感","dimension_name_en":"wok_hei_level","definition":"菜品的锅气程度等级 (0-5)","value_type":"数值","allowed_values":[0,1,2,3,4,5],"source_fields":["cooking_method","max_power"],"parse_method":"计算","remarks":"爆炒 + 高功率→高锅气","ui_component":"slider","default_value":3,"weight":1.0,"min_value":0,"max_value":5},
    {"dimension_id":"DEMAND_EXPERIENCE_009","domain":"需求端","dimension_name_cn":"干湿度","dimension_name_en":"moisture_level","definition":"菜品的干湿程度","value_type":"枚举","allowed_values":["干炒","半干","带汁","汤汁"],"source_fields":["cooking_method"],"parse_method":"规则","remarks":"炒→干炒，烧→带汁","ui_component":"select","default_value":"半干","weight":1.0},
    {"dimension_id":"DEMAND_EXPERIENCE_010","domain":"需求端","dimension_name_cn":"口感","dimension_name_en":"texture","definition":"菜品的主要口感特征","value_type":"多选","allowed_values":["脆","嫩","爽","软","糯","滑","酥"],"source_fields":["ingredients","cooking_method"],"parse_method":"模型","remarks":"AI 识别食材质地","ui_component":"multi-select","default_value":["嫩"],"weight":1.0},
    {"dimension_id":"DEMAND_EXPERIENCE_011","domain":"需求端","dimension_name_cn":"饱腹感","dimension_name_en":"satiety","definition":"菜品的饱腹程度","value_type":"枚举","allowed_values":["轻食","中等","强饱腹"],"source_fields":["ingredients","portion_size"],"parse_method":"计算","remarks":"主食占比 + 热量","ui_component":"select","default_value":"中等","weight":0.8},
    {"dimension_id":"DEMAND_PEOPLE_001","domain":"需求端","dimension_name_cn":"人数规格","dimension_name_en":"portion_size","definition":"菜谱的份量规格","value_type":"枚举","allowed_values":["1 人份","2 人份","3-4 人份","宴会份"],"source_fields":["ingredients","tags"],"parse_method":"规则","remarks":"根据食材总量判断","ui_component":"select","default_value":"3-4 人份","weight":1.0},
    {"dimension_id":"DEMAND_PEOPLE_002","domain":"需求端","dimension_name_cn":"饮食限制","dimension_name_en":"dietary_restrictions","definition":"菜谱适合的饮食限制","value_type":"多选","allowed_values":["低盐","低油","低糖","高蛋白","素食","清真"],"source_fields":["ingredients","tags"],"parse_method":"规则","remarks":"食材和标签分析","ui_component":"multi-select","default_value":[],"weight":0.9},
    {"dimension_id":"DEMAND_PEOPLE_003","domain":"需求端","dimension_name_cn":"过敏原","dimension_name_en":"allergens","definition":"菜品可能含有的过敏原","value_type":"多选","allowed_values":["花生","坚果","蛋","奶","海鲜","麸质"],"source_fields":["ingredients"],"parse_method":"模型","remarks":"AI 识别食材过敏原","ui_component":"multi-select","default_value":[],"weight":1.0},
    {"dimension_id":"DEMAND_PEOPLE_004","domain":"需求端","dimension_name_cn":"特殊偏好","dimension_name_en":"special_preferences","definition":"菜品的特殊偏好适配","value_type":"多选","allowed_values":["少辣","不葱姜蒜","不香菜","不内脏"],"source_fields":["ingredients","tags"],"parse_method":"规则","remarks":"可调整选项","ui_component":"multi-select","default_value":[],"weight":0.8},
    {"dimension_id":"DEMAND_REGION_001","domain":"需求端","dimension_name_cn":"国家菜系","dimension_name_en":"national_cuisine","definition":"菜谱的国家菜系归属","value_type":"枚举","allowed_values":["中餐","日餐","韩餐","东南亚","西餐"],"source_fields":["name","cuisine_type"],"parse_method":"规则","remarks":"菜系一级分类","ui_component":"select","default_value":"中餐","weight":1.0},
    {"dimension_id":"DEMAND_REGION_002","domain":"需求端","dimension_name_cn":"中国区域","dimension_name_en":"china_region","definition":"菜谱的中国地理区域归属","value_type":"枚举","allowed_values":["东北","华北","华东","华中","华南","西南","西北"],"source_fields":["cuisine_type"],"parse_method":"规则","remarks":"菜系映射区域","ui_component":"select","default_value":"华东","weight":1.0},
    {"dimension_id":"DEMAND_REGION_003","domain":"需求端","dimension_name_cn":"细分菜系","dimension_name_en":"sub_cuisine","definition":"菜谱的细分菜系","value_type":"枚举","allowed_values":["川","湘","粤","鲁","苏","浙","闽","徽"],"source_fields":["cuisine_type","name"],"parse_method":"模型","remarks":"AI+ 规则识别","ui_component":"select","default_value":"粤","weight":1.0},
    {"dimension_id":"DEMAND_REGION_004","domain":"需求端","dimension_name_cn":"地方风味标签","dimension_name_en":"local_flavor_tags","definition":"菜谱的地方风味特征","value_type":"多选","allowed_values":["家常","下饭","夜宵","小炒","干锅","红烧","清炒"],"source_fields":["name","tags","cooking_method"],"parse_method":"规则","remarks":"菜名和做法关键词","ui_component":"multi-select","default_value":["家常"],"weight":0.9},
    {"dimension_id":"DEMAND_COMPLEXITY_001","domain":"需求端","dimension_name_cn":"菜品感知复杂度","dimension_name_en":"perceived_complexity","definition":"用户感知的菜品复杂程度","value_type":"枚举","allowed_values":["简单","中等","复杂","专业"],"source_fields":["cook_time","steps","ingredients"],"parse_method":"计算","remarks":"步骤数 + 食材数综合","ui_component":"select","default_value":"中等","weight":1.0},
    {"dimension_id":"DEMAND_COMPLEXITY_002","domain":"需求端","dimension_name_cn":"感知制作门槛","dimension_name_en":"perceived_difficulty","definition":"用户感知的制作难度","value_type":"枚举","allowed_values":["家常","厨师型","宴会型"],"source_fields":["complexity","techniques"],"parse_method":"规则","remarks":"技法复杂度判断","ui_component":"select","default_value":"家常","weight":0.9},
    {"dimension_id":"DEMAND_COMPLEXITY_003","domain":"需求端","dimension_name_cn":"感知等待成本","dimension_name_en":"perceived_wait_cost","definition":"用户感知的等待时间成本","value_type":"枚举","allowed_values":["即点即出","可等","慢工菜"],"source_fields":["cook_time"],"parse_method":"规则","remarks":"<3min→即点即出","ui_component":"select","default_value":"可等","weight":0.8},
    {"dimension_id":"DELIVERY_DEVICE_001","domain":"交付端","dimension_name_cn":"总时长","dimension_name_en":"total_time","definition":"烹饪总时长（秒）","value_type":"数值","allowed_values":[],"source_fields":["cook_time"],"parse_method":"计算","remarks":"cook_time 字段直接映射","ui_component":"number","default_value":180,"weight":1.0,"min_value":0,"max_value":3600},
    {"dimension_id":"DELIVERY_DEVICE_002","domain":"交付端","dimension_name_cn":"功率曲线","dimension_name_en":"power_curve","definition":"功率随时间变化模式","value_type":"文本","allowed_values":[],"source_fields":["cook_steps"],"parse_method":"计算","remarks":"从 cook_steps 提取 type=3 步骤","ui_component":"chart","default_value":"","weight":1.0},
    {"dimension_id":"DELIVERY_DEVICE_003","domain":"交付端","dimension_name_cn":"温度曲线","dimension_name_en":"temperature_curve","definition":"温度随时间变化模式","value_type":"文本","allowed_values":[],"source_fields":["cook_steps","max_power"],"parse_method":"计算","remarks":"功率换算温度","ui_component":"chart","default_value":"","weight":0.9},
    {"dimension_id":"DELIVERY_DEVICE_004","domain":"交付端","dimension_name_cn":"搅拌速度","dimension_name_en":"stir_speed","definition":"搅拌速度等级","value_type":"枚举","allowed_values":["不搅拌","低速","中速","高速"],"source_fields":["cook_steps"],"parse_method":"规则","remarks":"从 speed 字段提取","ui_component":"select","default_value":"中速","weight":0.9},
    {"dimension_id":"DELIVERY_DEVICE_005","domain":"交付端","dimension_name_cn":"搅拌方向","dimension_name_en":"stir_direction","definition":"搅拌方向","value_type":"枚举","allowed_values":["正转","反转","交替"],"source_fields":["cook_steps"],"parse_method":"规则","remarks":"从 direction 字段提取","ui_component":"select","default_value":"正转","weight":0.8},
    {"dimension_id":"DELIVERY_DEVICE_006","domain":"交付端","dimension_name_cn":"锅位/工位","dimension_name_en":"position","definition":"锅位或工位设置","value_type":"枚举","allowed_values":["高锅位","中锅位","低锅位","热锅位","炒菜位"],"source_fields":["cook_steps"],"parse_method":"规则","remarks":"从 position 字段提取","ui_component":"select","default_value":"炒菜位","weight":0.9},
    {"dimension_id":"DELIVERY_DEVICE_007","domain":"交付端","dimension_name_cn":"加热阶段数","dimension_name_en":"heating_stages","definition":"加热阶段数量","value_type":"数值","allowed_values":[],"source_fields":["cook_steps"],"parse_method":"计算","remarks":"type=1 或 2 的步骤数","ui_component":"number","default_value":3,"weight":0.8,"min_value":1,"max_value":20},
    {"dimension_id":"DELIVERY_DEVICE_008","domain":"交付端","dimension_name_cn":"收汁阶段","dimension_name_en":"reduction_stage","definition":"收汁阶段配置","value_type":"布尔","allowed_values":[true,false],"source_fields":["cook_steps"],"parse_method":"规则","remarks":"是否有收汁步骤","ui_component":"toggle","default_value":false,"weight":0.7},
    {"dimension_id":"DELIVERY_DEVICE_009","domain":"交付端","dimension_name_cn":"爆香阶段","dimension_name_en":"aromatic_stage","definition":"爆香阶段配置","value_type":"布尔","allowed_values":[true,false],"source_fields":["cook_steps","ingredients"],"parse_method":"规则","remarks":"是否有爆香步骤","ui_component":"toggle","default_value":true,"weight":0.8},
    {"dimension_id":"DELIVERY_DEVICE_010","domain":"交付端","dimension_name_cn":"保温/结束逻辑","dimension_name_en":"keep_warm_logic","definition":"保温或结束策略","value_type":"枚举","allowed_values":["立即结束","保温 5min","保温 15min","保温 30min"],"source_fields":["cook_steps"],"parse_method":"规则","remarks":"最后一步配置","ui_component":"select","default_value":"立即结束","weight":0.6},
    {"dimension_id":"DELIVERY_DOSING_001","domain":"交付端","dimension_name_cn":"投料总次数","dimension_name_en":"total_dosing_count","definition":"投料总次数","value_type":"数值","allowed_values":[],"source_fields":["cooking_ingredient"],"parse_method":"计算","remarks":"食材数组长度","ui_component":"number","default_value":5,"weight":1.0,"min_value":1,"max_value":50},
    {"dimension_id":"DELIVERY_DOSING_002","domain":"交付端","dimension_name_cn":"自动投料次数","dimension_name_en":"auto_dosing_count","definition":"自动投料次数","value_type":"数值","allowed_values":[],"source_fields":["cooking_ingredient"],"parse_method":"计算","remarks":"auto=true 的食材数","ui_component":"number","default_value":3,"weight":0.9,"min_value":0,"max_value":50},
    {"dimension_id":"DELIVERY_DOSING_003","domain":"交付端","dimension_name_cn":"手动投料次数","dimension_name_en":"manual_dosing_count","definition":"手动投料次数","value_type":"数值","allowed_values":[],"source_fields":["cooking_ingredient"],"parse_method":"计算","remarks":"auto=false 的食材数","ui_component":"number","default_value":2,"weight":0.9,"min_value":0,"max_value":50},
    {"dimension_id":"DELIVERY_DOSING_004","domain":"交付端","dimension_name_cn":"投料顺序","dimension_name_en":"dosing_sequence","definition":"投料先后顺序","value_type":"文本","allowed_values":[],"source_fields":["cooking_ingredient"],"parse_method":"计算","remarks":"按 time 排序的食材列表","ui_component":"list","default_value":"","weight":1.0},
    {"dimension_id":"DELIVERY_DOSING_005","domain":"交付端","dimension_name_cn":"投料时机","dimension_name_en":"dosing_timing","definition":"每个投料点的时间（秒）","value_type":"文本","allowed_values":[],"source_fields":["cooking_ingredient"],"parse_method":"计算","remarks":"[{name, time}] 数组","ui_component":"timeline","default_value":"","weight":1.0},
    {"dimension_id":"DELIVERY_DOSING_006","domain":"交付端","dimension_name_cn":"单次投料量","dimension_name_en":"single_dosing_amount","definition":"每次投料克数","value_type":"数值","allowed_values":[],"source_fields":["cooking_ingredient"],"parse_method":"计算","remarks":"amount 字段汇总","ui_component":"number","default_value":0,"weight":0.9,"min_value":0,"max_value":5000},
    {"dimension_id":"DELIVERY_DOSING_007","domain":"交付端","dimension_name_cn":"投料方式","dimension_name_en":"dosing_method","definition":"投料方式","value_type":"枚举","allowed_values":["自动","手动","混合"],"source_fields":["cooking_ingredient"],"parse_method":"计算","remarks":"根据自动/手动比例","ui_component":"select","default_value":"混合","weight":0.9},
    {"dimension_id":"DELIVERY_DOSING_008","domain":"交付端","dimension_name_cn":"主料/辅料/调料分类","dimension_name_en":"ingredient_category","definition":"投料分类","value_type":"文本","allowed_values":[],"source_fields":["cooking_ingredient"],"parse_method":"规则","remarks":"category 字段映射","ui_component":"list","default_value":"","weight":0.8},
    {"dimension_id":"DELIVERY_DOSING_009","domain":"交付端","dimension_name_cn":"腌制料/爆香料/收口料","dimension_name_en":"functional_ingredient","definition":"功能分类","value_type":"文本","allowed_values":[],"source_fields":["cooking_ingredient","tags"],"parse_method":"规则","remarks":"功能标签分类","ui_component":"list","default_value":"","weight":0.7},
    {"dimension_id":"DELIVERY_PRODUCTION_001","domain":"交付端","dimension_name_cn":"适配机型","dimension_name_en":"compatible_models","definition":"适用的设备型号","value_type":"多选","allowed_values":["基础版","标准版","专业版","商用版"],"source_fields":["equipment","max_power"],"parse_method":"规则","remarks":"功率要求映射","ui_component":"multi-select","default_value":["标准版"],"weight":0.9},
    {"dimension_id":"DELIVERY_PRODUCTION_002","domain":"交付端","dimension_name_cn":"设备功率上限","dimension_name_en":"max_power_requirement","definition":"设备功率上限要求","value_type":"数值","allowed_values":[],"source_fields":["max_power"],"parse_method":"计算","remarks":"max_power 字段","ui_component":"number","default_value":2000,"weight":1.0,"min_value":0,"max_value":20000},
    {"dimension_id":"DELIVERY_PRODUCTION_003","domain":"交付端","dimension_name_cn":"是否依赖料仓","dimension_name_en":"requires_silo","definition":"是否依赖自动料仓","value_type":"布尔","allowed_values":[true,false],"source_fields":["cooking_ingredient","equipment"],"parse_method":"规则","remarks":"自动投料>3 次→是","ui_component":"toggle","default_value":false,"weight":0.8},
    {"dimension_id":"DELIVERY_PRODUCTION_004","domain":"交付端","dimension_name_cn":"是否依赖人工确认","dimension_name_en":"requires_manual_confirm","definition":"是否需要人工确认步骤","value_type":"布尔","allowed_values":[true,false],"source_fields":["cook_steps"],"parse_method":"规则","remarks":"有 manual 步骤→是","ui_component":"toggle","default_value":true,"weight":0.9},
    {"dimension_id":"DELIVERY_PRODUCTION_005","domain":"交付端","dimension_name_cn":"人工干预强度","dimension_name_en":"manual_intervention_level","definition":"人工干预强度等级","value_type":"枚举","allowed_values":["低","中","高"],"source_fields":["manual_count","cook_time"],"parse_method":"计算","remarks":"manual_count/cook_time 比率","ui_component":"select","default_value":"中","weight":0.9},
    {"dimension_id":"DELIVERY_PRODUCTION_006","domain":"交付端","dimension_name_cn":"并发可执行性","dimension_name_en":"concurrency","definition":"可并发执行数量","value_type":"数值","allowed_values":[],"source_fields":["equipment","cook_time"],"parse_method":"计算","remarks":"设备限制","ui_component":"number","default_value":1,"weight":0.7,"min_value":1,"max_value":10},
    {"dimension_id":"DELIVERY_PRODUCTION_007","domain":"交付端","dimension_name_cn":"高峰可交付性","dimension_name_en":"peak_deliverable","definition":"高峰期是否可交付","value_type":"布尔","allowed_values":[true,false],"source_fields":["cook_time","peak_pressure"],"parse_method":"规则","remarks":"cook_time<360s→是","ui_component":"toggle","default_value":true,"weight":0.8},
    {"dimension_id":"DELIVERY_PRODUCTION_008","domain":"交付端","dimension_name_cn":"出餐稳定性","dimension_name_en":"serving_stability","definition":"出餐稳定性等级","value_type":"枚举","allowed_values":["高","中","低"],"source_fields":["automation_ratio","manual_count"],"parse_method":"计算","remarks":"自动化率>80%→高","ui_component":"select","default_value":"中","weight":0.9},
    {"dimension_id":"DELIVERY_PRODUCTION_009","domain":"交付端","dimension_name_cn":"对原料波动敏感度","dimension_name_en":"ingredient_variance_sensitivity","definition":"对原料波动的敏感程度","value_type":"枚举","allowed_values":["高","中","低"],"source_fields":["ingredients","cook_steps"],"parse_method":"规则","remarks":"精细菜品→高敏感","ui_component":"select","default_value":"中","weight":0.7},
    {"dimension_id":"DELIVERY_OUTPUT_001","domain":"交付端","dimension_name_cn":"成品重量","dimension_name_en":"final_weight","definition":"出品克数","value_type":"数值","allowed_values":[],"source_fields":["ingredients","cook_time"],"parse_method":"计算","remarks":"食材总量 - 损耗","ui_component":"number","default_value":400,"weight":0.9,"min_value":0,"max_value":5000},
    {"dimension_id":"DELIVERY_OUTPUT_002","domain":"交付端","dimension_name_cn":"份量规格","dimension_name_en":"portion_spec","definition":"份量规格","value_type":"枚举","allowed_values":["1 人份","2 人份","3-4 人份","宴会份"],"source_fields":["ingredients"],"parse_method":"计算","remarks":"总重量映射","ui_component":"select","default_value":"3-4 人份","weight":0.9},
    {"dimension_id":"DELIVERY_OUTPUT_003","domain":"交付端","dimension_name_cn":"装盘方式","dimension_name_en":"plating_method","definition":"装盘方式","value_type":"枚举","allowed_values":["平铺","堆叠","淋汁","围边"],"source_fields":["tags","cuisine_type"],"parse_method":"规则","remarks":"菜系习惯","ui_component":"select","default_value":"平铺","weight":0.6},
    {"dimension_id":"DELIVERY_OUTPUT_004","domain":"交付端","dimension_name_cn":"容器类型","dimension_name_en":"container_type","definition":"出品容器类型","value_type":"枚举","allowed_values":["盘","碗","煲","锅","盅"],"source_fields":["name","cuisine_type"],"parse_method":"规则","remarks":"菜名关键词","ui_component":"select","default_value":"盘","weight":0.7},
    {"dimension_id":"DELIVERY_OUTPUT_005","domain":"交付端","dimension_name_cn":"出品颜色目标","dimension_name_en":"target_color","definition":"出品颜色目标","value_type":"文本","allowed_values":[],"source_fields":["ingredients","cooking_method"],"parse_method":"模型","remarks":"AI 识别目标色泽","ui_component":"color-picker","default_value":"","weight":0.6},
    {"dimension_id":"DELIVERY_OUTPUT_006","domain":"交付端","dimension_name_cn":"出品状态","dimension_name_en":"final_state","definition":"出品状态","value_type":"枚举","allowed_values":["干香","带汁","浓汁","汤菜"],"source_fields":["cooking_method","ingredients"],"parse_method":"规则","remarks":"烹饪方式决定","ui_component":"select","default_value":"带汁","weight":0.8},
    {"dimension_id":"CONTROL_TASTE_001","domain":"控制变量","dimension_name_cn":"盐量","dimension_name_en":"salt_amount","definition":"盐的用量（克）","value_type":"数值","allowed_values":[],"source_fields":["cooking_ingredient"],"parse_method":"计算","remarks":"盐 + 含盐调料","ui_component":"number","default_value":3,"weight":1.0,"min_value":0,"max_value":50,"unit":"g"},
    {"dimension_id":"CONTROL_TASTE_002","domain":"控制变量","dimension_name_cn":"糖量","dimension_name_en":"sugar_amount","definition":"糖的用量（克）","value_type":"数值","allowed_values":[],"source_fields":["cooking_ingredient"],"parse_method":"计算","remarks":"糖 + 含糖调料","ui_component":"number","default_value":2,"weight":1.0,"min_value":0,"max_value":100,"unit":"g"},
    {"dimension_id":"CONTROL_TASTE_003","domain":"控制变量","dimension_name_cn":"酸味料量","dimension_name_en":"acid_amount","definition":"酸味调料用量（克）","value_type":"数值","allowed_values":[],"source_fields":["cooking_ingredient"],"parse_method":"计算","remarks":"醋 + 柠檬等","ui_component":"number","default_value":0,"weight":0.9,"min_value":0,"max_value":50,"unit":"g"},
    {"dimension_id":"CONTROL_TASTE_004","domain":"控制变量","dimension_name_cn":"辣味料量","dimension_name_en":"spicy_amount","definition":"辣味调料用量（克）","value_type":"数值","allowed_values":[],"source_fields":["cooking_ingredient"],"parse_method":"计算","remarks":"辣椒/辣酱","ui_component":"number","default_value":0,"weight":1.0,"min_value":0,"max_value":100,"unit":"g"},
    {"dimension_id":"CONTROL_TASTE_005","domain":"控制变量","dimension_name_cn":"麻味料量","dimension_name_en":"numbing_amount","definition":"麻味调料用量（克）","value_type":"数值","allowed_values":[],"source_fields":["cooking_ingredient"],"parse_method":"计算","remarks":"花椒/麻椒","ui_component":"number","default_value":0,"weight":0.9,"min_value":0,"max_value":50,"unit":"g"},
    {"dimension_id":"CONTROL_TASTE_006","domain":"控制变量","dimension_name_cn":"鲜味料量","dimension_name_en":"umami_amount","definition":"鲜味调料用量（克）","value_type":"数值","allowed_values":[],"source_fields":["cooking_ingredient"],"parse_method":"计算","remarks":"鸡精/味精/蚝油","ui_component":"number","default_value":2,"weight":0.8,"min_value":0,"max_value":30,"unit":"g"},
    {"dimension_id":"CONTROL_TASTE_007","domain":"控制变量","dimension_name_cn":"酱香料量","dimension_name_en":"sauce_amount","definition":"酱料用量（克）","value_type":"数值","allowed_values":[],"source_fields":["cooking_ingredient"],"parse_method":"计算","remarks":"生抽/老抽/豆瓣","ui_component":"number","default_value":10,"weight":0.9,"min_value":0,"max_value":200,"unit":"g"},
    {"dimension_id":"CONTROL_TASTE_008","domain":"控制变量","dimension_name_cn":"油量","dimension_name_en":"oil_amount","definition":"食用油用量（克）","value_type":"数值","allowed_values":[],"source_fields":["cooking_ingredient"],"parse_method":"计算","remarks":"所有油脂","ui_component":"number","default_value":30,"weight":1.0,"min_value":0,"max_value":500,"unit":"g"},
    {"dimension_id":"CONTROL_HEAT_001","domain":"控制变量","dimension_name_cn":"初始火力","dimension_name_en":"initial_power","definition":"初始火力功率（W）","value_type":"数值","allowed_values":[],"source_fields":["cook_steps"],"parse_method":"计算","remarks":"第一步功率","ui_component":"number","default_value":2000,"weight":0.9,"min_value":0,"max_value":20000,"unit":"W"},
    {"dimension_id":"CONTROL_HEAT_002","domain":"控制变量","dimension_name_cn":"中段火力","dimension_name_en":"mid_power","definition":"中段火力功率（W）","value_type":"数值","allowed_values":[],"source_fields":["cook_steps"],"parse_method":"计算","remarks":"中间步骤功率","ui_component":"number","default_value":1500,"weight":0.8,"min_value":0,"max_value":20000,"unit":"W"},
    {"dimension_id":"CONTROL_HEAT_003","domain":"控制变量","dimension_name_cn":"末段火力","dimension_name_en":"final_power","definition":"末段火力功率（W）","value_type":"数值","allowed_values":[],"source_fields":["cook_steps"],"parse_method":"计算","remarks":"最后步骤功率","ui_component":"number","default_value":800,"weight":0.8,"min_value":0,"max_value":20000,"unit":"W"},
    {"dimension_id":"CONTROL_HEAT_004","domain":"控制变量","dimension_name_cn":"高火持续时间","dimension_name_en":"high_power_duration","definition":"高火持续时间（秒）","value_type":"数值","allowed_values":[],"source_fields":["cook_steps"],"parse_method":"计算","remarks":"功率>1500W 的时长","ui_component":"number","default_value":60,"weight":0.8,"min_value":0,"max_value":600,"unit":"s"},
    {"dimension_id":"CONTROL_HEAT_005","domain":"控制变量","dimension_name_cn":"收汁时长","dimension_name_en":"reduction_time","definition":"收汁时长（秒）","value_type":"数值","allowed_values":[],"source_fields":["cook_steps"],"parse_method":"规则","remarks":"收汁步骤时长","ui_component":"number","default_value":30,"weight":0.7,"min_value":0,"max_value":300,"unit":"s"},
    {"dimension_id":"CONTROL_HEAT_006","domain":"控制变量","dimension_name_cn":"爆香时长","dimension_name_en":"aromatic_time","definition":"爆香时长（秒）","value_type":"数值","allowed_values":[],"source_fields":["cook_steps"],"parse_method":"规则","remarks":"爆香步骤时长","ui_component":"number","default_value":15,"weight":0.8,"min_value":0,"max_value":120,"unit":"s"},
    {"dimension_id":"CONTROL_STRUCTURE_001","domain":"控制变量","dimension_name_cn":"主料下锅时机","dimension_name_en":"main_ingredient_timing","definition":"主料下锅时间（秒）","value_type":"数值","allowed_values":[],"source_fields":["cooking_ingredient"],"parse_method":"计算","remarks":"主料 time 字段","ui_component":"number","default_value":0,"weight":1.0,"min_value":0,"max_value":600,"unit":"s"},
    {"dimension_id":"CONTROL_STRUCTURE_002","domain":"控制变量","dimension_name_cn":"辅料下锅时机","dimension_name_en":"side_ingredient_timing","definition":"辅料下锅时间（秒）","value_type":"数值","allowed_values":[],"source_fields":["cooking_ingredient"],"parse_method":"计算","remarks":"辅料 time 字段","ui_component":"number","default_value":30,"weight":0.9,"min_value":0,"max_value":600,"unit":"s"},
    {"dimension_id":"CONTROL_STRUCTURE_003","domain":"控制变量","dimension_name_cn":"调味时机","dimension_name_en":"seasoning_timing","definition":"调味下锅时间（秒）","value_type":"数值","allowed_values":[],"source_fields":["cooking_ingredient"],"parse_method":"计算","remarks":"调料 time 字段","ui_component":"number","default_value":60,"weight":0.9,"min_value":0,"max_value":600,"unit":"s"},
    {"dimension_id":"CONTROL_STRUCTURE_004","domain":"控制变量","dimension_name_cn":"收口时机","dimension_name_en":"finishing_timing","definition":"收口下锅时间（秒）","value_type":"数值","allowed_values":[],"source_fields":["cooking_ingredient"],"parse_method":"计算","remarks":"收口料 time","ui_component":"number","default_value":150,"weight":0.7,"min_value":0,"max_value":600,"unit":"s"},
    {"dimension_id":"CONTROL_STRUCTURE_005","domain":"控制变量","dimension_name_cn":"同步投料/分步投料","dimension_name_en":"dosing_strategy","definition":"投料策略","value_type":"枚举","allowed_values":["同步投料","分步投料"],"source_fields":["cooking_ingredient"],"parse_method":"计算","remarks":"time 相同→同步","ui_component":"select","default_value":"分步投料","weight":0.9},
    {"dimension_id":"CONTROL_STRUCTURE_006","domain":"控制变量","dimension_name_cn":"搅拌强度","dimension_name_en":"stir_intensity","definition":"搅拌强度等级","value_type":"枚举","allowed_values":["低","中","高"],"source_fields":["cook_steps"],"parse_method":"规则","remarks":"speed 字段映射","ui_component":"select","default_value":"中","weight":0.8},
    {"dimension_id":"CONTROL_STRUCTURE_007","domain":"控制变量","dimension_name_cn":"搅拌频率","dimension_name_en":"stir_frequency","definition":"搅拌频率（次/分钟）","value_type":"数值","allowed_values":[],"source_fields":["cook_steps"],"parse_method":"计算","remarks":"搅拌次数/时长","ui_component":"number","default_value":10,"weight":0.7,"min_value":0,"max_value":60,"unit":"次/min"},
    {"dimension_id":"CONTROL_STABILITY_001","domain":"控制变量","dimension_name_cn":"人工步骤数量","dimension_name_en":"manual_steps_count","definition":"人工步骤数量","value_type":"数值","allowed_values":[],"source_fields":["cook_steps"],"parse_method":"计算","remarks":"type=manual 的步骤数","ui_component":"number","default_value":2,"weight":0.9,"min_value":0,"max_value":50},
    {"dimension_id":"CONTROL_STABILITY_002","domain":"控制变量","dimension_name_cn":"自动化覆盖率","dimension_name_en":"automation_ratio","definition":"自动化步骤占比（%）","value_type":"数值","allowed_values":[],"source_fields":["cook_steps"],"parse_method":"计算","remarks":"自动步骤/总步骤","ui_component":"progress","default_value":60,"weight":1.0,"min_value":0,"max_value":100,"unit":"%"},
    {"dimension_id":"CONTROL_STABILITY_003","domain":"控制变量","dimension_name_cn":"重复动作风险","dimension_name_en":"repetition_risk","definition":"重复动作风险等级","value_type":"枚举","allowed_values":["低","中","高"],"source_fields":["cook_steps"],"parse_method":"计算","remarks":"重复动作次数","ui_component":"select","default_value":"低","weight":0.7},
    {"dimension_id":"CONTROL_STABILITY_004","domain":"控制变量","dimension_name_cn":"同时事件数","dimension_name_en":"concurrent_events","definition":"同时发生的事件数量","value_type":"数值","allowed_values":[],"source_fields":["cook_steps"],"parse_method":"计算","remarks":"同一时间点的事件","ui_component":"number","default_value":1,"weight":0.7,"min_value":1,"max_value":10},
    {"dimension_id":"CONTROL_STABILITY_005","domain":"控制变量","dimension_name_cn":"对关键食材含水率敏感度","dimension_name_en":"moisture_sensitivity","definition":"对食材含水率的敏感程度","value_type":"枚举","allowed_values":["高","中","低"],"source_fields":["ingredients","cook_steps"],"parse_method":"规则","remarks":"叶菜类→高敏感","ui_component":"select","default_value":"中","weight":0.6},
    {"dimension_id":"CONTROL_STABILITY_006","domain":"控制变量","dimension_name_cn":"对预处理依赖度","dimension_name_en":"prep_dependency","definition":"对预处理的依赖程度","value_type":"枚举","allowed_values":["高","中","低"],"source_fields":["ingredients","tags"],"parse_method":"规则","remarks":"需腌制/切配→高","ui_component":"select","default_value":"中","weight":0.7},
    {"dimension_id":"CONTROL_KNOB_001","domain":"控制变量","dimension_name_cn":"辣度旋钮","dimension_name_en":"spiciness_knob","definition":"辣度调节旋钮 (0-5)","value_type":"数值","allowed_values":[0,1,2,3,4,5],"source_fields":["CONTROL_TASTE_004"],"parse_method":"映射","remarks":"辣味料量→0-5 映射","ui_component":"slider","default_value":0,"weight":1.0,"min_value":0,"max_value":5},
    {"dimension_id":"CONTROL_KNOB_002","domain":"控制变量","dimension_name_cn":"麻度旋钮","dimension_name_en":"numbing_knob","definition":"麻度调节旋钮 (0-5)","value_type":"数值","allowed_values":[0,1,2,3,4,5],"source_fields":["CONTROL_TASTE_005"],"parse_method":"映射","remarks":"麻味料量→0-5 映射","ui_component":"slider","default_value":0,"weight":1.0,"min_value":0,"max_value":5},
    {"dimension_id":"CONTROL_KNOB_003","domain":"控制变量","dimension_name_cn":"咸度旋钮","dimension_name_en":"saltiness_knob","definition":"咸度调节旋钮 (0-5)","value_type":"数值","allowed_values":[0,1,2,3,4,5],"source_fields":["CONTROL_TASTE_001"],"parse_method":"映射","remarks":"盐量→0-5 映射","ui_component":"slider","default_value":3,"weight":1.0,"min_value":0,"max_value":5},
    {"dimension_id":"CONTROL_KNOB_004","domain":"控制变量","dimension_name_cn":"甜度旋钮","dimension_name_en":"sweetness_knob","definition":"甜度调节旋钮 (0-5)","value_type":"数值","allowed_values":[0,1,2,3,4,5],"source_fields":["CONTROL_TASTE_002"],"parse_method":"映射","remarks":"糖量→0-5 映射","ui_component":"slider","default_value":0,"weight":1.0,"min_value":0,"max_value":5},
    {"dimension_id":"CONTROL_KNOB_005","domain":"控制变量","dimension_name_cn":"酸度旋钮","dimension_name_en":"sourness_knob","definition":"酸度调节旋钮 (0-5)","value_type":"数值","allowed_values":[0,1,2,3,4,5],"source_fields":["CONTROL_TASTE_003"],"parse_method":"映射","remarks":"酸味料量→0-5 映射","ui_component":"slider","default_value":0,"weight":1.0,"min_value":0,"max_value":5},
    {"dimension_id":"CONTROL_KNOB_006","domain":"控制变量","dimension_name_cn":"油量旋钮","dimension_name_en":"oil_knob","definition":"油量调节旋钮 (0-5)","value_type":"数值","allowed_values":[0,1,2,3,4,5],"source_fields":["CONTROL_TASTE_008"],"parse_method":"映射","remarks":"油量→0-5 映射","ui_component":"slider","default_value":3,"weight":0.9,"min_value":0,"max_value":5},
    {"dimension_id":"CONTROL_KNOB_007","domain":"控制变量","dimension_name_cn":"锅气旋钮","dimension_name_en":"wok_hei_knob","definition":"锅气调节旋钮 (0-5)","value_type":"数值","allowed_values":[0,1,2,3,4,5],"source_fields":["CONTROL_HEAT_001","CONTROL_HEAT_004"],"parse_method":"映射","remarks":"火力 + 时长→锅气","ui_component":"slider","default_value":3,"weight":1.0,"min_value":0,"max_value":5},
    {"dimension_id":"CONTROL_KNOB_008","domain":"控制变量","dimension_name_cn":"嫩度旋钮","dimension_name_en":"tenderness_knob","definition":"嫩度调节旋钮 (0-5)","value_type":"数值","allowed_values":[0,1,2,3,4,5],"source_fields":["CONTROL_HEAT_006","CONTROL_STRUCTURE_003"],"parse_method":"映射","remarks":"爆香 + 调味时机→嫩度","ui_component":"slider","default_value":3,"weight":0.9,"min_value":0,"max_value":5},
    {"dimension_id":"CONTROL_KNOB_009","domain":"控制变量","dimension_name_cn":"收汁程度旋钮","dimension_name_en":"reduction_knob","definition":"收汁程度旋钮 (0-5)","value_type":"数值","allowed_values":[0,1,2,3,4,5],"source_fields":["CONTROL_HEAT_005"],"parse_method":"映射","remarks":"收汁时长→0-5","ui_component":"slider","default_value":2,"weight":0.8,"min_value":0,"max_value":5},
    {"dimension_id":"CONTROL_KNOB_010","domain":"控制变量","dimension_name_cn":"色泽深浅旋钮","dimension_name_en":"color_knob","definition":"色泽深浅旋钮 (0-5)","value_type":"数值","allowed_values":[0,1,2,3,4,5],"source_fields":["CONTROL_TASTE_007"],"parse_method":"映射","remarks":"酱料量→色泽","ui_component":"slider","default_value":3,"weight":0.8,"min_value":0,"max_value":5},
    {"dimension_id":"CONTROL_KNOB_011","domain":"控制变量","dimension_name_cn":"出餐速度优先级","dimension_name_en":"speed_priority","definition":"出餐速度优先级","value_type":"枚举","allowed_values":["快","标准","慢"],"source_fields":["CONTROL_HEAT_001","CONTROL_HEAT_004"],"parse_method":"映射","remarks":"火力策略映射","ui_component":"select","default_value":"标准","weight":0.9},
    {"dimension_id":"CONTROL_KNOB_012","domain":"控制变量","dimension_name_cn":"自动化优先级","dimension_name_en":"automation_priority","definition":"自动化优先级","value_type":"枚举","allowed_values":["高","中","低"],"source_fields":["CONTROL_STABILITY_002"],"parse_method":"映射","remarks":"自动化率映射","ui_component":"select","default_value":"中","weight":0.9}
  ]
}
